MANIFEST.in
README
distribute_setup.py
setup.py
docs/build/html/command_ref.html
docs/build/html/developers.html
docs/build/html/history.html
docs/build/html/index.html
docs/build/html/install.html
docs/build/html/scripts.html
docs/build/html/search.html
docs/build/html/searchindex.js
docs/build/html/templates.html
docs/build/html/_sources/command_ref.txt
docs/build/html/_sources/developers.txt
docs/build/html/_sources/history.txt
docs/build/html/_sources/index.txt
docs/build/html/_sources/install.txt
docs/build/html/_sources/scripts.txt
docs/build/html/_sources/templates.txt
docs/build/html/_static/basic.css
docs/build/html/_static/contents.png
docs/build/html/_static/doctools.js
docs/build/html/_static/file.png
docs/build/html/_static/jquery.js
docs/build/html/_static/minus.png
docs/build/html/_static/nature.css
docs/build/html/_static/navigation.png
docs/build/html/_static/plus.png
docs/build/html/_static/pygments.css
docs/build/html/_static/searchtools.js
docs/build/html/_static/sphinxdoc.css
docs/build/html/_static/underscore.js
docs/source/command_ref.rst
docs/source/conf.py
docs/source/developers.rst
docs/source/history.rst
docs/source/index.rst
docs/source/install.rst
docs/source/scripts.rst
docs/source/templates.rst
docs/sphinx/web/templates/base.html
tests/run_tests
tests/shunit2
tests/test.sh
tests/test_activate.sh
tests/test_cd.sh
tests/test_mkproject.sh
tests/test_templates.sh
tests/trace.txt
tests/util.sh
virtualenvwrapper/__init__.py
virtualenvwrapper/project.py
virtualenvwrapper/project.sh
virtualenvwrapper.project.egg-info/PKG-INFO
virtualenvwrapper.project.egg-info/SOURCES.txt
virtualenvwrapper.project.egg-info/dependency_links.txt
virtualenvwrapper.project.egg-info/entry_points.txt
virtualenvwrapper.project.egg-info/namespace_packages.txt
virtualenvwrapper.project.egg-info/not-zip-safe
virtualenvwrapper.project.egg-info/top_level.txt