Metadata-Version: 1.1
Name: virtualenvwrapper.project
Version: 1.3
Summary: virtualenvwrapper plugin to manage a project work directory
Home-page: http://www.doughellmann.com/projects/virtualenvwrapper.project/
Author: Doug Hellmann
Author-email: doug.hellmann@gmail.com
License: UNKNOWN
Download-URL: http://www.doughellmann.com/downloads/virtualenvwrapper.project-1.3.tar.gz
Platform: Any
Classifier: Development Status :: 5 - Production/Stable
Classifier: License :: OSI Approved :: BSD License
Classifier: Programming Language :: Python
Classifier: Programming Language :: Python :: 2
Classifier: Programming Language :: Python :: 2.5
Classifier: Programming Language :: Python :: 2.6
Classifier: Programming Language :: Python :: 2.7
Classifier: Intended Audience :: Developers
Classifier: Environment :: Console
Requires: virtualenv
Requires: virtualenvwrapper (>=2.0)
Provides: virtualenvwrapper.project
